terminalcp/__init__.py
terminalcp/__main__.py
terminalcp/ansi.py
terminalcp/attach_client.py
terminalcp/cli.py
terminalcp/key_parser.py
terminalcp/mcp_server.py
terminalcp/messages.py
terminalcp/terminal_client.py
terminalcp/terminal_manager.py
terminalcp/terminal_server.py
terminalcp/completion/__init__.py
terminalcp/completion/detect.py
terminalcp/completion/install.py
terminalcp/completion/scripts/__init__.py
terminalcp/completion/scripts/_terminalcp.zsh
terminalcp/completion/scripts/terminalcp.bash
terminalcp/completion/scripts/terminalcp.fish
terminalcp-1.0.3.dist-info/METADATA
terminalcp-1.0.3.dist-info/WHEEL
terminalcp-1.0.3.dist-info/entry_points.txt
terminalcp-1.0.3.dist-info/RECORD
