Metadata-Version: 2.4
Name: terminalcp
Version: 1.0.3
Summary: MCP server for spawning and controlling background processes with virtual terminals (Python port)
Author: Mario Zechner
License: MIT
Requires-Python: >=3.10
Requires-Dist: mcp>=1.0.0
Requires-Dist: pyte>=0.8.2
